MANIFEST.in
README.rst
setup.py
sharc/__init__.py
sharc/sharc.py
sharc.egg-info/PKG-INFO
sharc.egg-info/SOURCES.txt
sharc.egg-info/dependency_links.txt
sharc.egg-info/top_level.txt