Metadata-Version: 1.0
Name: sharc
Version: 0.1.0
Summary: Sharded Counters for Google Appengine (GAE).
Home-page: http://github.com/kaste/sharc
Author: herr kaste
Author-email: herr.kaste@gmail.com
License: Apache 2
Download-URL: http://github.com/kaste/sharc/tarball/master#egg=sharc-dev
Keywords: google appengine gae sharded counter ndb
Platform: UNKNOWN
Classifier: Development Status :: 4 - Beta
Classifier: Environment :: Web Environment
Classifier: Intended Audience :: Developers
Classifier: License :: OSI Approved :: Apache Software License
Classifier: Operating System :: OS Independent
Classifier: Programming Language :: Python
Classifier: Topic :: Internet :: WWW/HTTP
Classifier: Topic :: Software Development :: Libraries
